booste/__init__ 2.py
booste/__init__.py
booste/clip_utils.py
booste/generics.py
booste/gpt2_utils.py
booste/package.py
booste-0.3.1.dist-info/METADATA
booste-0.3.1.dist-info/WHEEL
booste-0.3.1.dist-info/dependency_links 2.txt
booste-0.3.1.dist-info/top_level 2.txt
booste-0.3.1.dist-info/top_level.txt
booste-0.3.1.dist-info/RECORD
