Metadata-Version: 2.1
Name: booste
Version: 0.3.1
Summary: The booste package is a python client to interact with your machine learning models hosted on Booste
Home-page: https://www.booste.io
Author: Erik Dunteman
Author-email: erik@booste.io
License: MIT
Keywords: Booste client,API wrapper,Booste
Platform: UNKNOWN
Classifier: Development Status :: 3 - Alpha
Classifier: Intended Audience :: Developers
Classifier: Topic :: Software Development :: Build Tools
Classifier: License :: OSI Approved :: MIT License
Classifier: Programming Language :: Python :: 3.7
Classifier: Programming Language :: Python :: 3.8
Requires-Dist: certifi
Requires-Dist: chardet
Requires-Dist: idna
Requires-Dist: requests
Requires-Dist: urllib3
Requires-Dist: numpy
Requires-Dist: pillow
